docs/source/conf.py
docs/source/generate_examples.py
docs_env/bin/activate_this.py
docs_env/bin/rst2html.py
docs_env/bin/rst2html4.py
docs_env/bin/rst2html5.py
docs_env/bin/rst2latex.py
docs_env/bin/rst2man.py
docs_env/bin/rst2odt.py
docs_env/bin/rst2odt_prepstyles.py
docs_env/bin/rst2pseudoxml.py
docs_env/bin/rst2s5.py
docs_env/bin/rst2xetex.py
docs_env/bin/rst2xml.py
docs_env/bin/rstpep2html.py
examples/llms/litellm_complete.py
examples/llms/litellm_json_format.py
examples/llms/vllm_complete.py
examples/llms/vllm_json_format.py
examples/processors/pdf/agentic_doc_reader.py
examples/processors/pdf/docling_reader.py
examples/processors/pdf/dolphin_reader.py
examples/processors/pdf/markitdown_reader.py
examples/processors/pdf/megaparse_reader.py
examples/processors/pdf/megaparse_vision_reader.py
examples/processors/pdf/ocrflux_reader.py
examples/processors/png/dolphin_reader.py
examples/processors/png/markitdown_reader.py
examples/processors/png/ocrflux_reader.py
examples/rags/basic_rag/ingest.py
examples/rags/basic_rag/ingest_hf.py
examples/rags/basic_rag/search.py
examples/rags/basic_rag/search_hf.py
examples/rags/contextual_rag/ingest.py
examples/rags/contextual_rag/ingest_es.py
examples/rags/contextual_rag/search.py
examples/rags/contextual_rag/search_es.py
examples/rags/raft/gen_finetune_data.py
examples/rags/raft/ingest.py
examples/rags/raft/search.py
examples/reranker/chain_reranker.py
examples/reranker/diversity_reranker.py
examples/reranker/litellm+llm_reranker.py
examples/reranker/lost_in_the_middle_reranker.py
examples/reranker/vllm+llm_reranker.py
rag_colls/core/constants.py
rag_colls/core/functions.py
rag_colls/core/serialization.py
rag_colls/core/settings.py
rag_colls/core/utils.py
rag_colls/core/base/chunkers/base.py
rag_colls/core/base/database/bm25.py
rag_colls/core/base/database/vector_database.py
rag_colls/core/base/embeddings/base.py
rag_colls/core/base/embeddings/base_sparse.py
rag_colls/core/base/llms/base.py
rag_colls-0.2.0.20.dist-info/licenses/LICENSE
rag_colls-0.2.0.20.dist-info/METADATA
rag_colls-0.2.0.20.dist-info/WHEEL
rag_colls-0.2.0.20.dist-info/top_level.txt
rag_colls-0.2.0.20.dist-info/RECORD
