Metadata-Version: 2.4
Name: rag-colls
Version: 0.2.0.20
Summary: rag-colls - Implement recent advanced RAG techniques
Project-URL: Homepage, https://github.com/hienhayho/rag-colls
Project-URL: Issues, https://github.com/hienhayho/rag-colls/issues
Requires-Python: >=3.11
License-File: LICENSE
Requires-Dist: bm25s>=0.2.10
Requires-Dist: chromadb<2.0.0,>=0.6.3
Requires-Dist: datasets<4.1,>=3.0
Requires-Dist: elasticsearch[async]>=8.17.2
Requires-Dist: gdown>=5.2.0
Requires-Dist: html2text>=2024.2.26
Requires-Dist: jax[cpu]>=0.5.3
Requires-Dist: json-repair>=0.41.0
Requires-Dist: litellm>=1.65.0
Requires-Dist: llama-index-embeddings-openai>=0.3.1
Requires-Dist: loguru>=0.7.3
Requires-Dist: openpyxl>=3.1.5
Requires-Dist: pandas<2.3.2,>=2.2.0
Requires-Dist: platformdirs>=4.3.7
Requires-Dist: polars>=1.27.0
Requires-Dist: pymupdf>=1.25.4
Requires-Dist: python-docx>=1.1.2
Requires-Dist: rich>=13.9.4
Requires-Dist: setuptools>=78.1.0
Requires-Dist: tenacity>=9.0.0
Provides-Extra: dev
Requires-Dist: pre-commit>=4.2.0; extra == "dev"
Requires-Dist: pytest>=8.3.5; extra == "dev"
Provides-Extra: docs
Requires-Dist: esbonio>=0.12.0; extra == "docs"
Requires-Dist: myst-parser>=4.0.1; extra == "docs"
Provides-Extra: huggingface-embedding
Requires-Dist: llama-index-embeddings-huggingface>=0.5.2; extra == "huggingface-embedding"
Requires-Dist: accelerate>=1.6.0; extra == "huggingface-embedding"
Provides-Extra: vllm-llm
Requires-Dist: vllm==0.9.0; extra == "vllm-llm"
Provides-Extra: finetune
Requires-Dist: deepspeed>=0.16.8; extra == "finetune"
Requires-Dist: ms-swift>=3.4.1; extra == "finetune"
Requires-Dist: wandb>=0.19.11; extra == "finetune"
Provides-Extra: dolphin
Requires-Dist: accelerate==1.6.0; extra == "dolphin"
Requires-Dist: numpy; extra == "dolphin"
Requires-Dist: omegaconf==2.3.0; extra == "dolphin"
Requires-Dist: opencv-python==4.11.0.86; extra == "dolphin"
Requires-Dist: opencv-python-headless; extra == "dolphin"
Requires-Dist: pymupdf==1.26.4; extra == "dolphin"
Requires-Dist: timm==0.5.4; extra == "dolphin"
Requires-Dist: torch>=2.6.0; extra == "dolphin"
Requires-Dist: torchvision>=0.21.0; extra == "dolphin"
Requires-Dist: transformers<4.54.0; extra == "dolphin"
Requires-Dist: vllm==0.9.0; extra == "dolphin"
Requires-Dist: vllm-dolphin==0.1; extra == "dolphin"
Provides-Extra: ocrflux-py
Requires-Dist: ocrflux; extra == "ocrflux-py"
Dynamic: license-file
